{
  "openapi": "3.0.0",
  "info": {
    "title": "ESP32 ESP-NOW Management API",
    "description": "API for managing ESP-NOW peers, topics, and authentication with detailed error reporting.",
    "version": "1.1.0"
  },
  "servers": [
    {
      "url": "/",
      "description": "ESP32 Web Server"
    }
  ],
  "components": {
    "securitySchemes": {
      "bearerAuth": {
        "type": "http",
        "scheme": "bearer",
        "bearerFormat": "JWT"
      }
    },
    "schemas": {
      "Error": {
        "type": "object",
        "required": ["error"],
        "properties": {
          "error": {
            "type": "string",
            "example": "INVALID_REQUEST"
          }
        }
      },
      "PasswordRequest": {
        "type": "object",
        "required": ["password"],
        "properties": {
          "password": { "type": "string" }
        }
      },
      "LoginResponse": {
        "type": "object",
        "required": ["token"],
        "properties": {
          "token": {
            "type": "string",
            "description": "JWT authentication token"
          }
        }
      },
      "SetPmkRequest": {
        "type": "object",
        "required": ["pmk"],
        "properties": {
          "pmk": {
            "type": "string",
            "description": "Primary Master Key (hex format)"
          }
        }
      },
      "Peer": {
        "type": "object",
        "required": ["id", "name", "mac"],
        "properties": {
          "id": { "type": "string", "format": "uuid" },
          "name": { "type": "string" },
          "mac": { "type": "string" }
        }
      },
      "PeersListResponse": {
        "type": "object",
        "required": ["peers"],
        "properties": {
          "peers": {
            "type": "array",
            "items": { "$ref": "#/components/schemas/Peer" }
          }
        }
      },
      "AddPeerRequest": {
        "type": "object",
        "required": ["name", "mac", "lmk"],
        "properties": {
          "name": { "type": "string" },
          "mac": { "type": "string" },
          "lmk": { "type": "string" }
        }
      },
      "TopicList": {
        "type": "object",
        "required": ["topicList"],
        "properties": {
          "topicList": {
            "type": "array",
            "items": { "type": "string" }
          }
        }
      }
    },
    "responses": {
      "UnauthorizedError": {
        "description": "Unauthorized - Missing or invalid JWT token",
        "content": {
          "application/json": {
            "schema": { "$ref": "#/components/schemas/Error" },
            "example": { "error": "UNAUTHORIZED" }
          }
        }
      },
      "InvalidRequestError": {
        "description": "Bad Request - Invalid parameters or missing fields",
        "content": {
          "application/json": {
            "schema": { "$ref": "#/components/schemas/Error" },
            "example": { "error": "INVALID_REQUEST" }
          }
        }
      }
    }
  },
  "security": [{ "bearerAuth": [] }],
  "paths": {
    "/login": {
      "post": {
        "tags": ["Authentication"],
        "summary": "Authenticate and receive a JWT token",
        "security": [],
        "requestBody": {
          "required": true,
          "content": {
            "application/json": {
              "schema": { "$ref": "#/components/schemas/PasswordRequest" }
            }
          }
        },
        "responses": {
          "200": {
            "description": "Successful login",
            "content": {
              "application/json": {
                "schema": { "$ref": "#/components/schemas/LoginResponse" }
              }
            }
          },
          "400": { "$ref": "#/components/responses/InvalidRequestError" },
          "403": {
            "description": "Forbidden - Incorrect password",
            "content": {
              "application/json": {
                "schema": { "$ref": "#/components/schemas/Error" },
                "example": { "error": "WRONG_PASSWORD" }
              }
            }
          }
        }
      }
    },
    "/set-password": {
      "post": {
        "tags": ["Authentication"],
        "summary": "Set a new authentication password",
        "requestBody": {
          "required": true,
          "content": {
            "application/json": {
              "schema": { "$ref": "#/components/schemas/PasswordRequest" }
            }
          }
        },
        "responses": {
          "200": { "description": "Password updated successfully" },
          "400": { "$ref": "#/components/responses/InvalidRequestError" },
          "401": { "$ref": "#/components/responses/UnauthorizedError" }
        }
      }
    },
    "/set-pmk": {
      "post": {
        "tags": ["Configuration"],
        "summary": "Set the Primary Master Key (PMK)",
        "requestBody": {
          "required": true,
          "content": {
            "application/json": {
              "schema": { "$ref": "#/components/schemas/SetPmkRequest" }
            }
          }
        },
        "responses": {
          "200": { "description": "PMK set successfully" },
          "400": { "$ref": "#/components/responses/InvalidRequestError" },
          "401": { "$ref": "#/components/responses/UnauthorizedError" },
          "500": {
            "description": "Internal Server Error",
            "content": {
              "application/json": {
                "schema": { "$ref": "#/components/schemas/Error" },
                "example": { "error": "CANNOT_SET_PMK_TO_ESP_NOW" }
              }
            }
          }
        }
      }
    },
    "/peers": {
      "get": {
        "tags": ["Peers"],
        "summary": "Get list of peers",
        "responses": {
          "200": {
            "description": "List of peers",
            "content": {
              "application/json": {
                "schema": { "$ref": "#/components/schemas/PeersListResponse" }
              }
            }
          },
          "401": { "$ref": "#/components/responses/UnauthorizedError" }
        }
      },
      "post": {
        "tags": ["Peers"],
        "summary": "Add a new peer",
        "requestBody": {
          "required": true,
          "content": {
            "application/json": {
              "schema": { "$ref": "#/components/schemas/AddPeerRequest" }
            }
          }
        },
        "responses": {
          "200": { "description": "Peer added successfully" },
          "400": { "$ref": "#/components/responses/InvalidRequestError" },
          "401": { "$ref": "#/components/responses/UnauthorizedError" },
          "403": {
            "description": "Forbidden - Duplicate peer",
            "content": {
              "application/json": {
                "schema": { "$ref": "#/components/schemas/Error" },
                "example": { "error": "EXISTS" }
              }
            }
          },
          "500": {
            "description": "Server Error",
            "content": {
              "application/json": {
                "schema": { "$ref": "#/components/schemas/Error" },
                "examples": {
                  "LimitReached": { "value": { "error": "MAX_PEERS_REACHED" } },
                  "EspNowFail": {
                    "value": { "error": "CANNOT_ADD_TO_ESP_NOW" }
                  }
                }
              }
            }
          }
        }
      }
    },
    "/peers/{id}": {
      "delete": {
        "tags": ["Peers"],
        "parameters": [
          {
            "name": "id",
            "in": "path",
            "required": true,
            "schema": {
              "type": "string",
              "format": "uuid",
              "pattern": "^[0-9a-fA-F-]{36}$"
            }
          }
        ],
        "responses": {
          "200": { "description": "Deleted" },
          "401": { "$ref": "#/components/responses/UnauthorizedError" },
          "404": { "description": "Not Found" }
        }
      }
    },
    "/topics/{id}": {
      "get": {
        "tags": ["Topics"],
        "parameters": [
          {
            "name": "id",
            "in": "path",
            "required": true,
            "schema": { "type": "string", "format": "uuid" }
          }
        ],
        "responses": {
          "200": {
            "description": "Success",
            "content": {
              "application/json": {
                "schema": { "$ref": "#/components/schemas/TopicList" }
              }
            }
          },
          "401": { "$ref": "#/components/responses/UnauthorizedError" },
          "404": { "description": "Not Found" }
        }
      },
      "post": {
        "tags": ["Topics"],
        "parameters": [
          {
            "name": "id",
            "in": "path",
            "required": true,
            "schema": { "type": "string", "format": "uuid" }
          }
        ],
        "requestBody": {
          "required": true,
          "content": {
            "application/json": {
              "schema": { "$ref": "#/components/schemas/TopicList" }
            }
          }
        },
        "responses": {
          "200": { "description": "Topics updated" },
          "400": { "$ref": "#/components/responses/InvalidRequestError" },
          "401": { "$ref": "#/components/responses/UnauthorizedError" },
          "404": { "description": "Not Found" }
        }
      }
    }
  }
}
